README
setup.py
pylmc.egg-info/PKG-INFO
pylmc.egg-info/SOURCES.txt
pylmc.egg-info/dependency_links.txt
pylmc.egg-info/entry_points.txt
pylmc.egg-info/top_level.txt
pylmc.egg-info/zip-safe
src/__init__.py
src/assembler.py
src/interpreter.py
src/objectfile.py